[
    {
        "templateId": "5c0d77df3b508889842b7484",
        "cmps": [
            {
                "id": "0",
                "kind": "text",
                "type": "invaitorName",
                "data": {
                    "txt": "R.M.R invaits you",
                    "css": {
                        "color": "black",
                        "textAlign": "center",
                        "fontWeight": {
                            "isBold": false,
                            "value": "normal"
                        },
                        "fontFamily": "Oswald",
                        "fontSize": "18px"
                    }
                }
            },
            {
                "id": "1",
                "kind": "text",
                "type": "eventTitle",
                "isEdit": true,
                "data": {
                    "txt": "Tap TAKEOVER & ",
                    "css": {
                        "color": "gold",
                        "textAlign": "left",
                        "fontWeight": {
                            "isBold": false,
                            "value": "normal"
                        },
                        "fontFamily": "Satisfy",
                        "fontSize": "28px"
                    }
                }
            },
            {
                "id": "2",
                "kind": "text",
                "type": "eventTitle",
                "isEdit": true,
                "data": {
                    "txt": "MEETUP ",
                    "css": {
                        "color": "gold",
                        "textAlign": "center",
                        "fontWeight": {
                            "isBold": false,
                            "value": "normal"
                        },
                        "fontFamily": "Satisfy",
                        "fontSize": "34px"
                    }
                }
            },
            {
                "id": "3",
                "kind": "text",
                "type": "shortDescription",
                "isEdit": true,
                "data": {
                    "txt": "Join us to learn about VUE.JS",
                    "css": {
                        "color": "rgb(243, 195, 105)",
                        "textAlign": "left",
                        "fontWeight": {
                            "isBold": false,
                            "value": "normal"
                        },
                        "fontFamily": "Asap Condensed",
                        "fontSize": "16px"
                    }
                }
            },
            {
                "id": "4",
                "kind": "text",
                "type": "day",
                "isEdit": true,
                "data": {
                    "txt": {
                        "day": "",
                        "time": ""
                    },
                    "css": {
                        "color": "black",
                        "textAlign": "center",
                        "fontWeight": {
                            "isBold": false,
                            "value": "normal"
                        },
                        "fontFamily": "Asap Condensed",
                        "fontSize": "16px"
                    }
                }
            },
            {
                "id": "5",
                "kind": "text",
                "type": "location",
                "isEdit": true,
                "data": {
                    "txt": "Beer Garden,Tel Aviv, Israel",
                    "css": {
                        "color": "black",
                        "textAlign": "center",
                        "fontWeight": {
                            "isBold": false,
                            "value": "normal"
                        },
                        "fontFamily": "Asap Condensed",
                        "fontSize": "17px"
                    }
                }
            },
            {
                "id": "6",
                "kind": "cmp",
                "type": "attending",
                "isEdit": true,
                "data": {}
            }
        ],
        "generalStyle": {
            "backgroundImage": "url('https://i.imgur.com/TBKs12e.png')",
            "backgroundPosition": "center",
            "background-size": "cover",
            "padding": "80px"
        },
        "creatorId": 123456.0,
        "modifiedAt": "",
        "createdAt": "",
        "attends": []
    },
    {
        "templateId": "5c0d77df3b508889842b7485",
        "cmps": [
            {
                "id": "0",
                "kind": "text",
                "type": "invaitorName",
                "data": {
                    "txt": "You are cordially invited to attend",
                    "css": {
                        "color": "white",
                        "textAlign": "center",
                        "fontWeight": {
                            "isBold": false,
                            "value": "normal"
                        },
                        "fontFamily": "Charmonman",
                        "fontSize": "20px"
                    }
                }
            },
            {
                "id": "1",
                "kind": "text",
                "type": "eventTitle",
                "isEdit": true,
                "data": {
                    "txt": "Meital & Don Wedding ",
                    "css": {
                        "color": "white",
                        "textAlign": "center",
                        "fontFamily": "Charmonman",
                        "fontSize": "70px",
                        "fontWeight": {
                            "isBold": true,
                            "value": "bold"
                        },
                        "minHeight": "170px"
                    }
                }
            },
            {
                "id": "3",
                "kind": "text",
                "type": "day",
                "isEdit": true,
                "data": {
                    "txt": "01/12/2018",
                    "css": {
                        "color": "black",
                        "textAlign": "center",
                        "fontWeight": {
                            "isBold": false,
                            "value": "normal"
                        },
                        "fontFamily": "Asap Condensed",
                        "fontSize": "16px"
                    }
                }
            },
            {
                "id": "5",
                "kind": "cmp",
                "type": "countClock",
                "isEdit": true,
                "data": {
                    "date": "2019-07-06 08:15:00",
                    "css": {
                        "color": "black",
                        "textAlign": "center",
                        "fontWeight": {
                            "isBold": false,
                            "value": "normal"
                        },
                        "fontFamily": "Satisfy",
                        "fontSize": "18px"
                    }
                }
            },
            {
                "id": "6",
                "kind": "text",
                "type": "location",
                "isEdit": true,
                "data": {
                    "txt": "Nezer Sireni, Tel-Aviv",
                    "css": {
                        "color": "white",
                        "textAlign": "center",
                        "fontWeight": {
                            "isBold": false,
                            "value": "normal"
                        },
                        "fontFamily": "Charmonman",
                        "fontSize": "17px"
                    }
                }
            },
            {
                "id": "7",
                "kind": "cmp",
                "type": "mapCmp",
                "isEdit": true,
                "data": {
                    "markers": [],
                    "places": [],
                    "currentPlace": null,
                    "center": {
                        "lat": 45.508,
                        "lng": -73.587
                    }
                }
            }
        ],
        "generalStyle": {
            "backgroundImage": "url('https://images.pexels.com/photos/3880/couple-love-romantic-silhouette.jpg?auto=compress&cs=tinysrgb&dpr=2&h=650&w=940')",
            "backgroundPosition": "center",
            "background-size": "cover",
            "padding": "50px",
            "backgroundBlendMode": "multiply",
            "backgroundColor": "burlywood"
        },
        "creatorId": 898989,
        "modifiedAt": "",
        "createdAt": "",
        "attends": []
    },
    {
        "templateId": "5c0d77df3b508889842b7486",
        "cmps": [
            {
                "id": "0",
                "kind": "text",
                "type": "invaitorName",
                "isEdit": true,
                "data": {
                    "txt": "YOU ARE INVITED TO A",
                    "css": {
                        "color": "white",
                        "textAlign": "left",
                        "padding": "13px",
                        "margin": "0 auto",
                        "fontWeight": {
                            "isBold": true,
                            "value": "normal"
                        },
                        "fontFamily": "Oswald",
                        "fontSize": "27px"
                    }
                }
            },
            {
                "id": "1",
                "kind": "text",
                "type": "shortDescription",
                "isEdit": true,
                "data": {
                    "txt": "Join us For Rotem's 26th Birthday ",
                    "css": {
                        "color": "white",
                        "textAlign": "center",
                        "padding": "",
                        "paddingTop": "35px",
                        "margin": "",
                        "marginLeft": "189px",
                        "marginTop": "-88px",
                        "transform": "rotate(14deg)",
                        "fontWeight": {
                            "isBold": false,
                            "value": "normal"
                        },
                        "fontFamily": "Asap Condensed",
                        "fontSize": "20px"
                    }
                }
            },
            {
                "id": "2",
                "kind": "text",
                "type": "eventTitle",
                "isEdit": true,
                "data": {
                    "txt": "P O O L   P A R T Y",
                    "css": {
                        "color": "white",
                        "textAlign": "center",
                        "width": "100%",
                        "padding": "",
                        "paddingTop": "32px",
                        "margin": "",
                        "marginRight": "76px",
                        "fontWeight": {
                            "isBold": true,
                            "value": "normal"
                        },
                        "fontFamily": "fantasy",
                        "fontSize": "56px"
                    }
                }
            },
            {
                "id": "3",
                "kind": "text",
                "type": "day",
                "isEdit": true,
                "data": {
                    "txt": {
                        "date": "19/08/2018",
                        "time": "12:30"
                    },
                    "css": {
                        "color": "black",
                        "textAlign": "center",
                        "marginTop": "39px",
                        "fontWeight": {
                            "isBold": false,
                            "value": "normal"
                        },
                        "fontFamily": "Asap Condensed",
                        "fontSize": "16px"
                    }
                }
            },
            {
                "id": "4",
                "kind": "text",
                "type": "location",
                "isEdit": true,
                "data": {
                    "txt": "124 conch street,Bikini Bottom",
                    "css": {
                        "color": "black",
                        "textAlign": "center",
                        "padding": "",
                        "margin": "",
                        "marginLeft": "175px",
                        "marginTop": "35px",
                        "fontWeight": {
                            "isBold": false,
                            "value": "normal"
                        },
                        "fontFamily": "Asap Condensed",
                        "fontSize": "18px"
                    }
                }
            },
            {
                "id": 5,
                "kind": "cmp",
                "type": "attending",
                "isEdit": true,
                "data": {
                    "css": {
                        "padding": "",
                        "marginTop": "47px"
                    }
                }
            },
            {
                "id": "7",
                "kind": "background",
                "type": "template",
                "data": {
                    "css": {
                        "backgroundColor": "",
                        "backgroundImage": ""
                    }
                }
            }
        ],
        "generalStyle": {
            "backgroundImage": "url('https://i.ibb.co/cy10bP3/pool-template.png')",
            "backgroundPosition": "center",
            "background-size": "cover",
            "padding": "50px"
        },
        "creatorId": 565656,
        "modifiedAt": "",
        "createdAt": "",
        "attends": []
    },
    {
        "_id" : ObjectId("5c17496442a0b1ffe3f5e03f"),
        "templateId" : "5c0e0f72fae36922c467025c",
        "cmps" : [ 
            {
                "id" : "0",
                "kind" : "text",
                "type" : "invaitorName",
                "data" : {
                    "txt" : "Ruti invaits you",
                    "css" : {
                        "color" : "black",
                        "textAlign" : "center",
                        "fontWeight" : {
                            "isBold" : false,
                            "value" : "normal"
                        },
                        "fontFamily" : "Oswald",
                        "fontSize" : "18px"
                    }
                }
            }, 
            {
                "id" : "1",
                "kind" : "text",
                "type" : "eventTitle",
                "isEdit" : true,
                "data" : {
                    "txt" : "Get your Dance on ",
                    "css" : {
                        "color" : "black",
                        "textAlign" : "center",
                        "fontWeight" : {
                            "isBold" : false,
                            "value" : "normal"
                        },
                        "fontFamily" : "Satisfy",
                        "fontSize" : "28px"
                    }
                }
            }, 
            {
                "id" : "3",
                "kind" : "text",
                "type" : "shortDescription",
                "isEdit" : true,
                "data" : {
                    "txt" : "Learn how to dance in three simple steps",
                    "css" : {
                        "color" : "black",
                        "textAlign" : "center",
                        "fontWeight" : {
                            "isBold" : false,
                            "value" : "normal"
                        },
                        "fontFamily" : "Asap Condensed",
                        "fontSize" : "16px"
                    }
                }
            }, 
            {
                "id" : "4",
                "kind" : "text",
                "type" : "day",
                "isEdit" : true,
                "data" : {
                    "txt" : {
                        "day" : "",
                        "time" : ""
                    },
                    "css" : {
                        "color" : "black",
                        "textAlign" : "center",
                        "fontWeight" : {
                            "isBold" : false,
                            "value" : "normal"
                        },
                        "fontFamily" : "Asap Condensed",
                        "fontSize" : "16px"
                    }
                }
            }, 
            {
                "id" : "5",
                "kind" : "text",
                "type" : "location",
                "isEdit" : true,
                "data" : {
                    "txt" : "Beer Garden,Tel Aviv, Israel",
                    "css" : {
                        "color" : "black",
                        "textAlign" : "center",
                        "fontWeight" : {
                            "isBold" : false,
                            "value" : "normal"
                        },
                        "fontFamily" : "Asap Condensed",
                        "fontSize" : "17px"
                    }
                }
            }, 
            {
                "id" : "6",
                "kind" : "cmp",
                "type" : "attending",
                "isEdit" : true,
                "data" : {}
            }, 
            {
                "id" : "7",
                "kind" : "cmp",
                "type" : "social-media",
                "isEdit" : true,
                "data" : {}
            }
        ],
        "generalStyle" : {
            "backgroundImage" : "url('https://i.imgur.com/9rv7odL.png')",
            "backgroundPosition" : "center",
            "background-size" : "cover",
            "padding" : "80px 90px"
        },
        "creatorId" : 123456.0,
        "modifiedAt" : "",
        "createdAt" : "",
        "attends" : []
    }
]